<ModOps>

	<!-- all Crop Farms NW, OW, Enbesa -->
	<ModOp Type="merge" Path="//ModuleOwner[FarmType = 'PlantFarm']/ModuleBuildRadius" ModOpID="SetModuleRadiusVanillaFarms">
		<ModuleBuildRadius>45</ModuleBuildRadius>
	</ModOp>

  	<ImyaTweaks Title="Features of Free Farmfield Placement:" />
	<ImyaExpose Path="self::ModuleBuildRadius" ModOpID="SetModuleRadiusVanillaFarms" ExposeID="ModuleRadius of Cropfarms" Description="This Value sets the radius for all vanilla and modded crop farms, in which you can build the field modules." Kind="Slider">
		<SliderDefinition Min="0" Max="250" Stepping="5" />
	</ImyaExpose>

	<!-- all Crop Farms Hacienda -->
	<ModOp Type="merge" Path="//Asset[Template = 'Electrifiable_RecipeFarm_Taludas']/Values/ModuleOwner[FarmType = 'PlantFarm']/ModuleBuildRadius | //Asset[Template = 'RecipeFarm']/Values/ModuleOwner[FarmType = 'PlantFarm']/ModuleBuildRadius | //Values[Pausable/IsHaciendaDependent]/ModuleOwner[FarmType = 'PlantFarm']/ModuleBuildRadius" ModOpID="SetModuleRadiusVanillaHaciendaFarms">
		<ModuleBuildRadius>25</ModuleBuildRadius>
	</ModOp>

	<ImyaExpose Path="self::ModuleBuildRadius" ModOpID="SetModuleRadiusVanillaHaciendaFarms" ExposeID="ModuleRadius of Hacienda Farms" Description="This Value sets the radius for all vanilla and modded Hacienda crop farms, in which you can build the field modules." Kind="Slider">
		<SliderDefinition Min="0" Max="250" Stepping="5" />
	</ImyaExpose>

	<!-- all Animal Farms -->
	<ModOp Type="merge" Path="//Values/ModuleOwner[FarmType = 'AnimalFarm']/ModuleBuildRadius" ModOpID="SetModuleRadiusVanillaAnimalFarms">
		<ModuleBuildRadius>15</ModuleBuildRadius>
	</ModOp>

	<ModOp Type="add" GUID="101269,5457" Path="/Values/ModuleOwner" ModOpID="SetModuleRadiusVanillaAnimalFarms">
		<ModuleBuildRadius>15</ModuleBuildRadius>
	</ModOp>	

	<ImyaExpose Path="self::ModuleBuildRadius" ModOpID="SetModuleRadiusVanillaAnimalFarms" ExposeID="ModuleRadius of Animal Farms" Description="This Value sets the radius for all vanilla and modded animal farms, in which you can build the field modules." Kind="Slider">
		<SliderDefinition Min="0" Max="250" Stepping="5" />
	</ImyaExpose>

</ModOps>